pdutils/__init__.py
pdutils/graphing/dfplot_line.py
pdutils/summary/dfunique.py
pdutils/utilities/__init__.py
pdutils/utilities/check_dtypes.py
pdutils/utilities/check_input.py
pdutils/utilities/parse_range.py
pdutils/utilities/set_axis_range.py
pdutility-0.1.4.dist-info/LICENSE.txt
pdutility-0.1.4.dist-info/METADATA
pdutility-0.1.4.dist-info/WHEEL
pdutility-0.1.4.dist-info/top_level.txt
pdutility-0.1.4.dist-info/RECORD
