Metadata-Version: 2.1
Name: pdutility
Version: 0.1.4
Summary: Pandas utility library - major release pending
Author-email: techds <chet_singh@berkeley.edu>
Project-URL: Demopage, https://github.com/techds/structured-data-processing-demos
Classifier: Programming Language :: Python :: 3
Classifier: License :: OSI Approved :: MIT License
Classifier: Operating System :: OS Independent
License-File: LICENSE.txt
